katana_render_submitter/__init__.py
katana_render_submitter/core.py
katana_render_submitter/ui.py
katana_render_submitter/util.py
katana_render_submitter/Tabs/katana_render_submitter_tab.py
KatanaRenderSubmitter-0.0.1.dist-info/METADATA
KatanaRenderSubmitter-0.0.1.dist-info/WHEEL
KatanaRenderSubmitter-0.0.1.dist-info/top_level.txt
KatanaRenderSubmitter-0.0.1.dist-info/RECORD
