Metadata-Version: 2.1
Name: KatanaRenderSubmitter
Version: 0.0.1
Summary: Render submitter for Katana
Home-page: https://github.com/thelightersguild/KatanaRenderSubmitter
Author: jlonghurst
License: UNKNOWN
Platform: UNKNOWN
Classifier: Programming Language :: Python :: 3
